[
	{
		"title": "Shampoo",
		"description": "limpieza",
		"code": "abc3",
		"price": 300,
		"status": true,
		"stock": 10,
		"category": "Higiene",
		"thumbnail": [],
		"id": 1
	},
	{
		"title": "Shampoo",
		"description": "limpieza",
		"code": "abc4",
		"price": 300,
		"status": true,
		"stock": 10,
		"category": "Higiene",
		"thumbnail": [],
		"id": 2
	},
	{
		"title": "Shampoo",
		"description": "limpieza",
		"code": "abc5",
		"price": 300,
		"status": true,
		"stock": 10,
		"category": "Higiene",
		"thumbnail": [],
		"id": 3
	}
]